bio_commons.py
version.py
bio_dataset_manager/bio_dataloader.py
bio_dataset_manager/bio_dataset.py
bio_sequences/bio_sequence.py
bio_sequences/bio_sequences_config.py
bio_sequences/bio_sequences_utils.py
bio_sequences/dna_sequence.py
bio_sequences/protein_sequence.py
bio_sequences/smiles_sequence.py
bio_dataset_manager-0.1.4.dist-info/LICENSE
bio_dataset_manager-0.1.4.dist-info/METADATA
bio_dataset_manager-0.1.4.dist-info/WHEEL
bio_dataset_manager-0.1.4.dist-info/entry_points.txt
bio_dataset_manager-0.1.4.dist-info/top_level.txt
bio_dataset_manager-0.1.4.dist-info/RECORD
