Metadata-Version: 2.2
Name: bio_dataset_manager
Version: 0.1.4
Summary: A small package to manage biological data.
Author-email: Fabio Bove <fabio.bove.dr@gmail.com>
License: GNU GENERAL PUBLIC LICENSE
Project-URL: Homepage, https://github.com/fabiobove-dr/bio_dataset_manager
Project-URL: Issues, https://github.com/fabiobove-dr/bio_dataset_manager/issues
Keywords: bio-informatics,data,manipulation
Requires-Python: <3.12,>=3.11
License-File: LICENSE
Requires-Dist: numpy<2.0.0,>=1.0.0
Requires-Dist: pandas>=2.2.3
Requires-Dist: tqdm>=4.67.1
Requires-Dist: scipy>=1.15.2
Requires-Dist: biopython~=1.84
Requires-Dist: viennarna>=2.6.4
Requires-Dist: rdkit>=2024.9.5
Requires-Dist: torch>=2.3.1
Provides-Extra: test
Requires-Dist: pytest>=7.3.2; extra == "test"
Requires-Dist: pytest-cov>=5.0.0; extra == "test"
Requires-Dist: pytest-mock>=3.14.0; extra == "test"
Provides-Extra: cuda
Requires-Dist: torch==2.3.1+cu121; extra == "cuda"
